<?xml version="1.0" encoding="utf-8"?>
<TextureAtlas imagePath="GF_DATE.png">
	<!-- Created with Adobe Animate version 22.0.4.185 -->
	<!-- http://www.adobe.com/products/animate.html -->
	<SubTexture name="GF Dancing Beat0000" x="0" y="0" width="292" height="409" frameX="-20" frameY="-17" frameWidth="336" frameHeight="426"/>
	<SubTexture name="GF Dancing Beat0001" x="0" y="0" width="292" height="409" frameX="-20" frameY="-17" frameWidth="336" frameHeight="426"/>
	<SubTexture name="GF Dancing Beat0002" x="302" y="0" width="295" height="407" frameX="-18" frameY="-19" frameWidth="336" frameHeight="426"/>
	<SubTexture name="GF Dancing Beat0003" x="607" y="0" width="295" height="406" frameX="-18" frameY="-19" frameWidth="336" frameHeight="426"/>
	<SubTexture name="GF Dancing Beat0004" x="912" y="0" width="295" height="410" frameX="-19" frameY="-15" frameWidth="336" frameHeight="426"/>
	<SubTexture name="GF Dancing Beat0005" x="1217" y="0" width="295" height="409" frameX="-19" frameY="-15" frameWidth="336" frameHeight="426"/>
	<SubTexture name="GF Dancing Beat0006" x="1522" y="0" width="297" height="411" frameX="-21" frameY="-13" frameWidth="336" frameHeight="426"/>
	<SubTexture name="GF Dancing Beat0007" x="0" y="421" width="323" height="423" frameX="-11" frameY="-1" frameWidth="336" frameHeight="426"/>
	<SubTexture name="GF Dancing Beat0008" x="0" y="421" width="323" height="423" frameX="-11" frameY="-1" frameWidth="336" frameHeight="426"/>
	<SubTexture name="GF Dancing Beat0009" x="0" y="421" width="323" height="423" frameX="-11" frameY="-1" frameWidth="336" frameHeight="426"/>
	<SubTexture name="GF Dancing Beat0010" x="333" y="421" width="333" height="424" frameX="-2" frameY="0" frameWidth="336" frameHeight="426"/>
	<SubTexture name="GF Dancing Beat0011" x="333" y="421" width="333" height="424" frameX="-2" frameY="0" frameWidth="336" frameHeight="426"/>
	<SubTexture name="GF Dancing Beat0012" x="333" y="421" width="333" height="424" frameX="-2" frameY="0" frameWidth="336" frameHeight="426"/>
	<SubTexture name="GF Dancing Beat0013" x="676" y="421" width="335" height="423" frameX="0" frameY="-1" frameWidth="336" frameHeight="426"/>
	<SubTexture name="GF Dancing Beat0014" x="676" y="421" width="335" height="423" frameX="0" frameY="-1" frameWidth="336" frameHeight="426"/>
	<SubTexture name="GF Dancing Beat0015" x="1021" y="421" width="328" height="414" frameX="-3" frameY="-12" frameWidth="336" frameHeight="426"/>
	<SubTexture name="GF Dancing Beat0016" x="1021" y="421" width="328" height="414" frameX="-3" frameY="-12" frameWidth="336" frameHeight="426"/>
	<SubTexture name="GF Dancing Beat0017" x="1359" y="421" width="324" height="414" frameX="-5" frameY="-12" frameWidth="336" frameHeight="426"/>
	<SubTexture name="GF Dancing Beat0018" x="1693" y="421" width="324" height="413" frameX="-5" frameY="-12" frameWidth="336" frameHeight="426"/>
	<SubTexture name="GF Dancing Beat0019" x="0" y="855" width="321" height="414" frameX="-7" frameY="-11" frameWidth="336" frameHeight="426"/>
	<SubTexture name="GF Dancing Beat0020" x="331" y="855" width="321" height="413" frameX="-7" frameY="-11" frameWidth="336" frameHeight="426"/>
	<SubTexture name="GF Dancing Beat0021" x="662" y="855" width="323" height="414" frameX="-10" frameY="-10" frameWidth="336" frameHeight="426"/>
	<SubTexture name="GF Dancing Beat0022" x="995" y="855" width="299" height="418" frameX="-37" frameY="-6" frameWidth="336" frameHeight="426"/>
	<SubTexture name="GF Dancing Beat0023" x="995" y="855" width="299" height="418" frameX="-37" frameY="-6" frameWidth="336" frameHeight="426"/>
	<SubTexture name="GF Dancing Beat0024" x="995" y="855" width="299" height="418" frameX="-37" frameY="-6" frameWidth="336" frameHeight="426"/>
	<SubTexture name="GF Dancing Beat0025" x="1304" y="855" width="298" height="417" frameX="-37" frameY="-7" frameWidth="336" frameHeight="426"/>
	<SubTexture name="GF Dancing Beat0026" x="1304" y="855" width="298" height="417" frameX="-37" frameY="-7" frameWidth="336" frameHeight="426"/>
	<SubTexture name="GF Dancing Beat0027" x="1304" y="855" width="298" height="417" frameX="-37" frameY="-7" frameWidth="336" frameHeight="426"/>
	<SubTexture name="GF Dancing Beat0028" x="1612" y="855" width="298" height="417" frameX="-37" frameY="-7" frameWidth="336" frameHeight="426"/>
	<SubTexture name="GF Dancing Beat0029" x="1612" y="855" width="298" height="417" frameX="-37" frameY="-7" frameWidth="336" frameHeight="426"/>
</TextureAtlas>
