<?xml version="1.0" encoding="utf-8"?>
<TextureAtlas imagePath="Bf-Christmas.png">
	<!-- Created with Adobe Animate version 22.0.4.185 -->
	<!-- http://www.adobe.com/products/animate.html -->
	<SubTexture name="anger-with-trauma.png" x="0" y="0" width="409" height="245"/>
	<SubTexture name="angry.png" x="419" y="0" width="409" height="245"/>
	<SubTexture name="annoyed.png" x="0" y="255" width="409" height="245"/>
	<SubTexture name="default.png" x="419" y="255" width="409" height="245"/>
	<SubTexture name="sparkle-eyes.png" x="0" y="510" width="409" height="245"/>
	<SubTexture name="the-rock.png" x="419" y="510" width="409" height="245"/>
	<SubTexture name="thud.png" x="0" y="765" width="409" height="245"/>
	<SubTexture name="traumatized.png" x="419" y="765" width="409" height="245"/>
</TextureAtlas>
